urbansim_wfrc/__init__.py
urbansim_wfrc/accounts.py
urbansim_wfrc/exceptions.py
urbansim_wfrc/developer/__init__.py
urbansim_wfrc/developer/developer.py
urbansim_wfrc/developer/sqftproforma.py
urbansim_wfrc/maps/__init__.py
urbansim_wfrc/maps/dframe_explorer.py
urbansim_wfrc/models/__init__.py
urbansim_wfrc/models/dcm.py
urbansim_wfrc/models/developer.py
urbansim_wfrc/models/regression.py
urbansim_wfrc/models/relocation.py
urbansim_wfrc/models/sqftproforma.py
urbansim_wfrc/models/supplydemand.py
urbansim_wfrc/models/transition.py
urbansim_wfrc/models/util.py
urbansim_wfrc/urbanchoice/__init__.py
urbansim_wfrc/urbanchoice/interaction.py
urbansim_wfrc/urbanchoice/mnl.py
urbansim_wfrc/urbanchoice/pmat.py
urbansim_wfrc/urbanchoice/relocation.py
urbansim_wfrc/utils/__init__.py
urbansim_wfrc/utils/logutil.py
urbansim_wfrc/utils/misc.py
urbansim_wfrc/utils/networks.py
urbansim_wfrc/utils/sampling.py
urbansim_wfrc/utils/testing.py
urbansim_wfrc/utils/yamlio.py
urbansim_wfrc-0.4.5.dist-info/METADATA
urbansim_wfrc-0.4.5.dist-info/WHEEL
urbansim_wfrc-0.4.5.dist-info/top_level.txt
urbansim_wfrc-0.4.5.dist-info/RECORD
