Metadata-Version: 2.4
Name: urbansim_wfrc
Version: 0.4.5
Summary: Urbansim library originally by Paul Waddell, customized by WFRC Analytics
Home-page: https://github.com/WFRCAnalytics/urbansim-wfrc
Author: WFRC_Analytics
Author-email: josh.reynolds@wfrc.utah.gov
Classifier: Intended Audience :: Science/Research
Classifier: Topic :: Scientific/Engineering :: Information Analysis
Classifier: Programming Language :: Python :: 3
Classifier: Programming Language :: Python :: 3.5
Classifier: Programming Language :: Python :: 3.6
Classifier: Programming Language :: Python :: 3.7
Classifier: Programming Language :: Python :: 3.8
Classifier: License :: OSI Approved :: BSD License
Requires-Python: >=3.6
Requires-Dist: orca_wfrc>=0.0.1
Requires-Dist: patsy>=0.4.1
Requires-Dist: prettytable>=0.7.2
Requires-Dist: pyyaml>=3.10
Requires-Dist: scipy>=1.0
Requires-Dist: simpledbf>=0.2.6
Requires-Dist: statsmodels<0.11,>=0.8; python_version < "3.6"
Requires-Dist: statsmodels>=0.8; python_version >= "3.6"
Requires-Dist: toolz>=0.8.1
Requires-Dist: zbox
Dynamic: author
Dynamic: author-email
Dynamic: classifier
Dynamic: description
Dynamic: description-content-type
Dynamic: home-page
Dynamic: requires-dist
Dynamic: requires-python
Dynamic: summary
